vscenv/__init__.py
vscenv/vscenv.py
vscenv-0.1.2.dist-info/LICENSE
vscenv-0.1.2.dist-info/METADATA
vscenv-0.1.2.dist-info/WHEEL
vscenv-0.1.2.dist-info/entry_points.txt
vscenv-0.1.2.dist-info/top_level.txt
vscenv-0.1.2.dist-info/RECORD
