Metadata-Version: 2.1
Name: vscenv
Version: 0.1.2
Summary: Isolate your vscode environment and keep it simple!
Home-page: https://github.com/jugangdae/vscenv
Author: Gangdae Ju
Author-email: jugangdae@gamil.com
License: MIT
Keywords: vscenv,manage,isolated,vscode,environment,simple,cli,tool
Classifier: Programming Language :: Python :: 3
Classifier: Programming Language :: Python :: 3.2
Classifier: Programming Language :: Python :: 3.3
Classifier: Programming Language :: Python :: 3.4
Classifier: Programming Language :: Python :: 3.5
Classifier: Programming Language :: Python :: 3.6
Classifier: Programming Language :: Python :: 3.7
Classifier: Programming Language :: Python :: 3.8
Classifier: Programming Language :: Python :: 3.9
Classifier: Programming Language :: Python :: 3.10
Classifier: Programming Language :: Python :: 3.11
Requires-Python: >=3
License-File: LICENSE
